setup.py
rottentomatoes/__init__.py
rottentomatoes/rottentomatoes.py
rottentomatoes.egg-info/PKG-INFO
rottentomatoes.egg-info/SOURCES.txt
rottentomatoes.egg-info/dependency_links.txt
rottentomatoes.egg-info/top_level.txt